LICENSE
README.rst
VERSION.txt
setup.py
src/lovely/ws/status/__init__.py
src/lovely/ws/status/probestatus.py
src/lovely/ws/status/statehandler.py
src/lovely/ws/status/svcstatus.py
src/lovely_ws_status.egg-info/PKG-INFO
src/lovely_ws_status.egg-info/SOURCES.txt
src/lovely_ws_status.egg-info/dependency_links.txt
src/lovely_ws_status.egg-info/namespace_packages.txt
src/lovely_ws_status.egg-info/requires.txt
src/lovely_ws_status.egg-info/top_level.txt
src/lovely_ws_status.egg-info/zip-safe