Metadata-Version: 1.1
Name: lovely-ws-status
Version: 1.0.0
Summary: Service Status Utilities for Pyramid Apps
Home-page: https://github.com/lovelysystems/lovely-ws-status
Author: Lovely Systems
Author-email: office@lovelysystems.com
License: Apache License 2.0
Keywords: pyramid service status monitoring prometheus
Platform: UNKNOWN
Classifier: Programming Language :: Python :: 3.4
Classifier: Programming Language :: Python :: 3.5
Classifier: Programming Language :: Python :: 3.6
Classifier: Programming Language :: Python :: 3.7
Classifier: Framework :: Pyramid
